nn4mc/__init__.py
nn4mc/analysis/__init__.py
nn4mc/analysis/analysis.py
nn4mc/datastructures/__init__.py
nn4mc/datastructures/layer/__init__.py
nn4mc/datastructures/layer/_globals.py
nn4mc/datastructures/layer/_layer.py
nn4mc/datastructures/layer/_weights.py
nn4mc/datastructures/neuralNetwork/__init__.py
nn4mc/datastructures/neuralNetwork/_neural_network.py
nn4mc/generator/__init__.py
nn4mc/generator/code_generator/__init__.py
nn4mc/generator/code_generator/_code_generator.py
nn4mc/generator/code_generator/_globals.py
nn4mc/generator/code_generator/templates/c_standard/include/activations.h.template
nn4mc/generator/code_generator/templates/c_standard/include/functions.h.template
nn4mc/generator/code_generator/templates/c_standard/include/nn4mc.h.template
nn4mc/generator/code_generator/templates/c_standard/include/padding.h.template
nn4mc/generator/code_generator/templates/c_standard/include/parameters.h.template
nn4mc/generator/code_generator/templates/c_standard/include/layers/activation.h.template
nn4mc/generator/code_generator/templates/c_standard/include/layers/conv1d.h.template
nn4mc/generator/code_generator/templates/c_standard/include/layers/conv2d.h.template
nn4mc/generator/code_generator/templates/c_standard/include/layers/dense.h.template
nn4mc/generator/code_generator/templates/c_standard/include/layers/gru.h.template
nn4mc/generator/code_generator/templates/c_standard/include/layers/lstm.h.template
nn4mc/generator/code_generator/templates/c_standard/include/layers/maxpooling1d.h.template
nn4mc/generator/code_generator/templates/c_standard/include/layers/maxpooling2d.h.template
nn4mc/generator/code_generator/templates/c_standard/include/layers/simplernn.h.template
nn4mc/generator/code_generator/templates/c_standard/src/activations.cpp.template
nn4mc/generator/code_generator/templates/c_standard/src/functions.cpp.template
nn4mc/generator/code_generator/templates/c_standard/src/nn4mc.cpp.template
nn4mc-0.3.0.dist-info/LICENSE.md
nn4mc-0.3.0.dist-info/METADATA
nn4mc-0.3.0.dist-info/WHEEL
nn4mc-0.3.0.dist-info/top_level.txt
nn4mc-0.3.0.dist-info/RECORD
