Metadata-Version: 2.1
Name: nn4mc
Version: 0.3.0
Summary: Neural Networks for Microcontrollers (nn4mc) is a Python package for generating microcontroller code in c from pre-trained models. Our intended audience is roboticists looking to embed intelligence into their applications; however, anyone interested in using a neural network in a microcontroller will find this software useful.
Home-page: https://github.com/correlllab/nn4mc_py
Author: Cooper Simpson, Sarah Manzano, Dana Hughes
Author-email: cooper.simpson@colorado.edu
License: MIT
Keywords: Neural Network,Microcontroller
Platform: UNKNOWN
Classifier: Programming Language :: Python :: 3
Classifier: License :: OSI Approved :: MIT License
Classifier: Operating System :: OS Independent
Classifier: Development Status :: 3 - Alpha
Classifier: Topic :: Software Development :: Code Generators
License-File: LICENSE.md
Requires-Dist: h5py
Requires-Dist: numpy
